LICENSE
README
setup.py
doc/pyncomings.conf
pyncomings/__init__.py
pyncomings/incomingsmanager.py
pyncomings.egg-info/PKG-INFO
pyncomings.egg-info/SOURCES.txt
pyncomings.egg-info/dependency_links.txt
pyncomings.egg-info/top_level.txt
pyncomings/dao/DAOsqlite3.py
pyncomings/dao/__init__.py
pyncomings/parsers/__init__.py
pyncomings/parsers/extendedlog.py
pyncomings/parsers/wowzaerrorlog.py
pyncomings/parsers/xferlog.py
test/unittest_pyncomings.py
tools/pyncomings
tools/pyncomings-garbage-collector
tools/pyncomings-sanitizer