Metadata-Version: 1.1
Name: pyncomings
Version: 0.3.6
Summary: Log entries parser
Home-page: https://tracker.interoud.com/sistemas/
Author: Pablo Saavedra Rodinho
Author-email: saavedra.pablo@interoud.com
License: Copyright (c) 2007 Pablo Saavedra Rodiño
